numpydoc_validation/_.py
numpydoc_validation/__init__.py
numpydoc_validation/_validate.py
numpydoc_validation-0.1.0.dist-info/WHEEL
numpydoc_validation-0.1.0.dist-info/METADATA
numpydoc_validation-0.1.0.dist-info/RECORD
